powercmd/__init__.py
powercmd/cmd.py
powercmd/command.py
powercmd/command_invoker.py
powercmd/command_line.py
powercmd/commands_dict.py
powercmd/completer.py
powercmd/exceptions.py
powercmd/extra_typing.py
powercmd/match_string.py
powercmd/split_list.py
powercmd/utils.py
powercmd-0.3.6.dist-info/LICENSE.md
powercmd-0.3.6.dist-info/METADATA
powercmd-0.3.6.dist-info/WHEEL
powercmd-0.3.6.dist-info/top_level.txt
powercmd-0.3.6.dist-info/zip-safe
powercmd-0.3.6.dist-info/RECORD
